iam_syncr
