Metadata-Version: 1.0
Name: iam-syncr
Version: 0.4.2
Summary: Syncs iam roles
Home-page: UNKNOWN
Author: Stephen Moore
Author-email: stephen@rea-group.com
License: MIT
Keywords: iam amazon credentials
Platform: UNKNOWN
